.bzrignore
LICENSE.GPL
LICENSE.txt
README.txt
bootstrap.py
buildout.cfg
jsmath-3.4f-xhtml.patch
setup.py
src/zw/__init__.py
src/zw.jsmath.egg-info/PKG-INFO
src/zw.jsmath.egg-info/SOURCES.txt
src/zw.jsmath.egg-info/dependency_links.txt
src/zw.jsmath.egg-info/namespace_packages.txt
src/zw.jsmath.egg-info/not-zip-safe
src/zw.jsmath.egg-info/requires.txt
src/zw.jsmath.egg-info/top_level.txt
src/zw/jsmath/__init__.py
src/zw/jsmath/configure.zcml
src/zw/jsmath/zw.jsmath-configure.zcml