Metadata-Version: 1.0
Name: zw.jsmath
Version: 3.4f-0.9
Summary: jsMath integration into zope3
Home-page: https://launchpad.net/zw.jsmath
Author: Gregor Giesen
Author-email: giesen@zaehlwerk.net
License: GPLv3
Keywords: zope3
Platform: UNKNOWN
Classifier: Development Status :: 4 - Beta
Classifier: Programming Language :: Python
Classifier: Environment :: Web Environment
Classifier: Topic :: Internet :: WWW/HTTP :: WSGI :: Application
Classifier: Framework :: Zope3
Classifier: Intended Audience :: Developers
Classifier: License :: OSI Approved :: GNU General Public License (GPL)
